dashlab/__init__.py
dashlab/_internal.py
dashlab/_version.py
dashlab/base.py
dashlab/core.py
dashlab/patches.py
dashlab/utils.py
dashlab/widgets.py
dashlab/static/animator.css
dashlab/static/animator.js
dashlab/static/fscreen.css
dashlab/static/fscreen.js
dashlab/static/listw.css
dashlab/static/listw.js
dashlab-0.3.8.dist-info/licenses/LICENSE
dashlab-0.3.8.dist-info/METADATA
dashlab-0.3.8.dist-info/WHEEL
dashlab-0.3.8.dist-info/top_level.txt
dashlab-0.3.8.dist-info/RECORD
