Metadata-Version: 2.4
Name: dashlab
Version: 0.3.8
Summary: A Python package for dashboard and data visualization tools.
Author-email: Abdul Saboor <asaboor.my@outlook.com>
License-Expression: MIT
Project-URL: Homepage, https://github.com/asaboor-gh/dashlab
Project-URL: Bug-Tracker, https://github.com/asaboor-gh/dashlab/issues
Keywords: Dashboard,Data Visualization,Python,Analytics
Classifier: Programming Language :: Python :: 3
Classifier: Programming Language :: Python :: 3.9
Classifier: Programming Language :: Python :: 3.10
Classifier: Programming Language :: Python :: 3.11
Classifier: Programming Language :: Python :: 3.12
Classifier: Operating System :: OS Independent
Classifier: Development Status :: 5 - Production/Stable
Classifier: Intended Audience :: Developers
Classifier: Topic :: Software Development :: Libraries :: Python Modules
Classifier: Topic :: Scientific/Engineering :: Visualization
Requires-Python: >=3.9
License-File: LICENSE
Requires-Dist: anywidget
Requires-Dist: markdown
Provides-Extra: extra
Dynamic: license-file
